odoo8_addon_sale_order_merge-8.0.1.0.0-py2.7-nspkg.pth
odoo8_addon_sale_order_merge-8.0.1.0.0.dist-info/top_level.txt
odoo8_addon_sale_order_merge-8.0.1.0.0.dist-info/WHEEL
odoo8_addon_sale_order_merge-8.0.1.0.0.dist-info/RECORD
odoo8_addon_sale_order_merge-8.0.1.0.0.dist-info/metadata.json
odoo8_addon_sale_order_merge-8.0.1.0.0.dist-info/DESCRIPTION.rst
odoo8_addon_sale_order_merge-8.0.1.0.0.dist-info/METADATA
odoo8_addon_sale_order_merge-8.0.1.0.0.dist-info/namespace_packages.txt
odoo_addons/sale_order_merge/__openerp__.py
odoo_addons/sale_order_merge/__init__.py
odoo_addons/sale_order_merge/README.rst
odoo_addons/sale_order_merge/models/sale_order.py
odoo_addons/sale_order_merge/models/__init__.py
odoo_addons/sale_order_merge/models/sale_order_merge.py
odoo_addons/sale_order_merge/i18n/nl.po
odoo_addons/sale_order_merge/views/sale_order.xml
odoo_addons/sale_order_merge/views/sale_order_merge.xml
odoo_addons/sale_order_merge/tests/test_sale_order_merge.py
odoo_addons/sale_order_merge/tests/__init__.py
