Metadata-Version: 2.0
Name: odoo8-addon-sale-order-merge
Version: 8.0.1.0.0
Summary: Merge sale orders that are confirmed, invoiced or delivered
Home-page: https://github.com/oca/sale-workflow
Author: UNKNOWN
Author-email: UNKNOWN
License: AGPL-3
Platform: UNKNOWN
Requires-Dist: odoo (<9.0a,>=8.0a)
Classifier: Programming Language :: Python :: 2.7
Classifier: Framework :: Odoo
Classifier: License :: OSI Approved :: GNU Affero General Public License v3
